email_auth_checker/__init__.py
email_auth_checker/cli.py
email_auth_checker/email_auth.py
email_auth_checker/reports.py
email_auth_checker-1.0.1.dist-info/licenses/LICENSE
email_auth_checker-1.0.1.dist-info/METADATA
email_auth_checker-1.0.1.dist-info/WHEEL
email_auth_checker-1.0.1.dist-info/entry_points.txt
email_auth_checker-1.0.1.dist-info/top_level.txt
email_auth_checker-1.0.1.dist-info/RECORD
